snaql_migration/__init__.py
snaql_migration/snaql_migration.py
snaql_migration/tests/__init__.py
snaql_migration/tests/test_config.py
snaql_migration/tests/test_migrations.py
snaql_migration-0.1.0.dist-info/DESCRIPTION.rst
snaql_migration-0.1.0.dist-info/METADATA
snaql_migration-0.1.0.dist-info/RECORD
snaql_migration-0.1.0.dist-info/WHEEL
snaql_migration-0.1.0.dist-info/entry_points.txt
snaql_migration-0.1.0.dist-info/metadata.json
snaql_migration-0.1.0.dist-info/top_level.txt
