Metadata-Version: 2.0
Name: snaql-migration
Version: 0.1.0
Summary: Lightweight SQL schema migration tool, based on Snaql query builder
Home-page: https://github.com/komissarex/snaql-migration
Author: Egor Komissarov
Author-email: komissarex@gmail.com
License: MIT
Platform: UNKNOWN
Requires-Dist: PyYAML (==3.11)
Requires-Dist: click (==6.3)
Requires-Dist: snaql (==0.3.5)
